serieset/__init__.py
serieset/dataset.py
serieset-0.1.2.dist-info/METADATA
serieset-0.1.2.dist-info/WHEEL
serieset-0.1.2.dist-info/top_level.txt
serieset-0.1.2.dist-info/RECORD
