Metadata-Version: 2.1
Name: serieset
Version: 0.1.2
Summary: Easy Time Series Dataset with PyTorch.
Home-page: https://github.com/liaoyuhua/serieset
Author: liaoyuhua
Author-email: ml.liaoyuhua@gmail.com
Classifier: Programming Language :: Python :: 3
Classifier: License :: OSI Approved :: MIT License
Classifier: Operating System :: OS Independent
Requires-Python: >=3.8
Requires-Dist: pandas >=1.4.0
Requires-Dist: numpy >=1.24.4
Requires-Dist: torch >=1.9.0
